django_interval/__init__.py
django_interval/fields.py
django_interval/filters.py
django_interval/urls.py
django_interval/utils.py
django_interval/views.py
django_interval/widgets.py
django_interval/static/css/intervalwidget.css
django_interval/static/js/intervalwidget.js
django_interval/templates/django_interval/inline_interval.html
django_interval/templates/django_interval/interval.html
django_interval/templates/django_interval/widgets/multiwidget.html
django_interval/templatetags/django_interval.py
django_interval-0.5.3.dist-info/METADATA
django_interval-0.5.3.dist-info/WHEEL
django_interval-0.5.3.dist-info/licenses/LICENSE.txt
django_interval-0.5.3.dist-info/RECORD
