Metadata-Version: 2.4
Name: django-interval
Version: 0.5.3
Summary: A Django field for storing fuzzy date information
Project-URL: source, https://github.com/acdh-oeaw/django-interval
Project-URL: changelog, https://github.com/acdh-oeaw/django-interval/blob/main/CHANGELOG.md
Project-URL: issues, https://github.com/acdh-oeaw/django-interval/issues
Author-email: Matthias Schlögl <matthias.schloegl@oeaw.ac.at>, Birger Schacht <birger.schacht@oeaw.ac.at>, K Kollmann <dev-kk@oeaw.ac.at>, Saranya Balasubramanian <saranya.balasubramanian@oeaw.ac.at>
License-Expression: MIT
License-File: LICENSE.txt
Requires-Python: >=3.11
Requires-Dist: django>=4
